Workbook

Sheet README
A1: Veolia - investment capacity to 31/12/2027 under the leverage commitment
A2: Capstone Subject 2 - perimeter: Financial capacity. Workshop 2 working model.
A4: Question: how much can Veolia commit to acquisitions between 1 July 2026 and 31 December 2027 while ending 2027 at net debt / EBITDA <= 3.0x?
A6: How to read it
A7: Inputs - every hard-coded number, with document, PDF page and how it was derived. Blue = input, yellow = judgement call to defend.
A8: Spent - Block 1: what has gone out against the EUR 4bn GreenUp envelope, gross and net of disposals.
A9: Start - Block 2: starting position (net debt, EBITDA, leverage, maturities, liquidity) and the two net-debt figures that do not reconcile.
A10: Engine - Blocks 3-4: one column per case. Green cells link to Inputs; blue cells in a case column are that case's overrides.
A11: Summary - the capacity range by case and the three sources of capacity (retained FCF, disposals, leverage headroom).
A12: Formulas - the four standard formulas (leverage, headroom, available cash, practical capacity) applied and corrected.
A13: Tornado - Block 5: one-way sensitivities ranked by swing, computed from the Engine.
A14: Rating - cross-check against the agency trigger (Moody's FFO/net debt). Low confidence until the PDF is read.
... A23: Rule followed: no number in this workbook was typed in as a result. Results are formulas over sourced inputs.

Sheet Summary
A1: Investment capacity to 31/12/2027 - summary (EUR m)
A3: Line | B3: Base | C3: GreenUp met | D3: Downside | E3: Upside
A4: NFD 30/06/2026 (actual) | B4: =Engine!$B$5 -> 24548 | C4: =Engine!$C$5 -> 24548 | D4: =Engine!$D$5 -> 24548 | E4: =Engine!$E$5 -> 24548
A5: NFD 31/12/2026e | B5: =Engine!$B$54 -> 22982.1 | C5: =Engine!$C$54 -> 22982.1 | D5: =Engine!$D$54 -> 23100 | E5: =Engine!$E$54 -> 22882.1
A6: Leverage 31/12/2026e | B6: =Engine!$B$56 -> 3.0771385 | C6: =Engine!$C$56 -> 3.0771385 | D6: =Engine!$D$56 -> 3.0929245 | E6: =Engine!$E$56 -> 3.0637492
A7: Check vs 2026 guidance | B7: =Engine!$B$57 -> consistent | C7: =Engine!$C$57 -> consistent | D7: =Engine!$D$57 -> consistent | E7: =Engine!$E$57 -> consistent
A8: EBITDA 2027e | B8: =Engine!$B$61 -> 7848.3759 | C8: =Engine!$C$61 -> 7910 | D8: =Engine!$D$61 -> 7788.0153 | E8: =Engine!$E$61 -> 7913.7365
A9: NFD 31/12/2027e before new M&A | B9: =Engine!$B$58 -> 22191.863 | C9: =Engine!$C$58 -> 22191.863 | D9: =Engine!$D$58 -> 23045.835 | E9: =Engine!$E$58 -> 21691.863
A10: Leverage 31/12/2027e before new M&A | B10: =Engine!$B$62 -> 2.8275739 | C10: =Engine!$C$62 -> 2.8055453 | D10: =Engine!$D$62 -> 2.9591409 | E10: =Engine!$E$62 -> 2.7410393
A11: Maximum NFD at cap | B11: =Engine!$B$63 -> 23545.128 | C11: =Engine!$C$63 -> 23730 | D11: =Engine!$D$63 -> 23364.046 | E11: =Engine!$E$63 -> 23741.209
A12: Leverage headroom (debt room) | B12: =Engine!$B$64 -> 1353.2647 | C12: =Engine!$C$64 -> 1538.137 | D12: =Engine!$D$64 -> 318.21127 | E12: =Engine!$E$64 -> 2049.3464
A13: ACQUISITION CAPACITY (EV) | B13: =Engine!$B$65 -> 1353.2647 | C13: =Engine!$C$65 -> 1538.137 | D13: =Engine!$D$65 -> 318.21127 | E13: =Engine!$E$65 -> 2927.6378
A14: Source 1 - retained FCF | B14: =Engine!$B$66 -> 856.13698 | C14: =Engine!$C$66 -> 856.13698 | D14: =Engine!$D$66 -> 502.16537 | E14: =Engine!$E$66 -> 856.13698
A15: Source 2 - disposals net of EBITDA lost | B15: =Engine!$B$67 -> 1230 | C15: =Engine!$C$67 -> 1230 | D15: =Engine!$D$67 -> 775 | E15: =Engine!$E$67 -> 1700
A16: Source 3 - leverage room vs Jun-26 debt | B16: =Engine!$B$68 -> -732.87232 | C16: =Engine!$C$68 -> -548 | D16: =Engine!$D$68 -> -958.9541 | E16: =Engine!$E$68 -> -506.79053
A17: Source 4 - pro forma uplift | B17: =Engine!$B$69 -> 0 | C17: =Engine!$C$69 -> 0 | D17: =Engine!$D$69 -> 0 | E17: =Engine!$E$69 -> 878.29133
A19: Range across the four cases
A20: Low | B20: =MIN(B13:E13) -> 318.21127
A21: High | B21: =MAX(B13:E13) -> 2927.6378
A23: Block 1 cross-reference: EUR 4bn envelope remaining (gross / net readings)
A24: Gross / net of disposals | B24: =Spent!$C$22 -> -1721 | C24: =Spent!$C$23 -> -602

Sheet Formulas
A1: Capacity with the four standard formulas (base case, EUR m)
A3: 1-2. Net leverage and debt headroom TODAY (30/06/2026, last-12-months EBITDA)
A4: Net leverage = net debt / EBITDA | B4: =Inputs!$C$3/Start!E3 -> 3.3929509 | C4: June debt peak / LTM EBITDA.
A5: Debt headroom = Lmax x EBITDA - net debt | B5: =Inputs!$C$52*Start!E3-Inputs!$C$3 -> -2843 | C5: Negative: on today's figures there is no room. Misleading: June is the seasonal peak and no future cash is counted.
A6: 1-2. Same formulas at the TEST DATE (31/12/2027, base-case forecast before new deals)
A7: Net leverage = net debt / EBITDA | B7: =Engine!$B$62 -> 2.8275739 | C7: The 3x is tested at year-end on Veolia's own definition (no bank covenant at parent level: FY25 p.67).
A8: Debt headroom = Lmax x EBITDA 2027 - net debt end-2027 | B8: =Engine!$B$64 -> 1353.2647 | C8: Net debt end-2027 already includes cash from operations, dividends and disposals.
A9: 3. Cash available for investment, Jul-2026 to Dec-2027
A10: + Opening cash (incl. liquid assets) | B10: =Inputs!$C$59 -> 9332
A11: + Cash generated: net FCF H2-26 + 2027 | B11: =Engine!$B$45+Engine!$B$46 -> 2697.9716 | C11: Net FCF is after capex, interest and tax.
A12: - Dividends, hybrid coupons, buyback | B12: =-(Engine!$B$47+Engine!$B$18+Engine!$B$50) -> -1841.8346
A13: + Disposal proceeds | B13: =Engine!$B$51 -> 1500
A14: + Permitted borrowing (undrawn committed lines) | B14: =Inputs!$C$60 -> 5873 | C14: Excludes new bond issues: Veolia raised EUR 3.9bn in H1-2026, so this is prudent.
A15: - Repayments (current debt + H2-2027 maturities) | B15: =-(Inputs!$C$61+Inputs!$C$62*Inputs!$C$63) -> -13319.5 | C15: Assumes nothing is refinanced.
A16: - Committed spending | B16: =-Inputs!$C$65 -> 0
A17: - Minimum cash reserve | B17: =-Inputs!$C$64 -> -2000
A18: Available cash (total) | B18: =SUM(B10:B17) -> 2241.637 | C18: Before any refinancing in the bond market.
A19: 4. Practical investment capacity
A20: As written: min(available cash, headroom + cash from operations) - committed | B20: =MIN(B18,B8+B11+B12)-Inputs!$C$65 -> 2209.4016 | C20: Overstates: the end-2027 headroom already contains the cash from operations, so it is counted twice.
A21: Corrected: min(available cash, end-2027 headroom) - committed | B21: =MIN(B18,B8)-Inputs!$C$65 -> 1353.2647 | C21: Headroom taken from the full net-debt forecast at the test date, as the note to formula 4 recommends.
A22: Binding constraint | B22: =IF(B18<B8,"Cash","Leverage (3x)") -> Leverage (3x)
A23: If acquired EBITDA counts in the 2027 ratio (deal at the input multiple) | B23: =MIN(B18,B8/(1-Inputs!$C$52/Inputs!$C$54))-Inputs!$C$65 -> 1933.2352 | C23: Each EUR 1 of EV buys 1/multiple of EBITDA, which raises the limit by 3/multiple.

Sheet Inputs
A1: Key | B1: Input | C1: Value | D1: Unit | E1: Source document | F1: PDF page | G1: Derivation / note | H1: Confidence
A2: Starting position
A3: NFD_J26 | B3: Net financial debt 30/06/2026 | C3: 24548 | D3: EUR m | E3: Amendment to 2025 URD - Half-year report 30/06/2026 | F3: 26 | G3: Closing NFD, Veolia definition (excl. Suez PPA remeasurement). Bridge table 3.3.1. | H3: High
A4: NFD_D25 | B4: Net financial debt 31/12/2025 (bridge basis) | C4: 19657 | D4: EUR m | E4: Amendment to 2025 URD - Half-year report 30/06/2026 | F4: 25-26 | G4: Opening NFD in the H1-2026 bridge. | H4: High
A5: NFD_D25s | B5: Net financial debt 31/12/2025 (statutory note) | C5: 19821 | D5: EUR m | E5: Consolidated financial statements 31/12/2025 | F5: 66 | G5: Note 8.3.2.1. Also shown as 12/31/2025 in H1-2026 key figures (p.6). Gap vs bridge basis = Suez PPA remeasurement (to confirm). | H5: High
A6: NFD_D24 | B6: Net financial debt 31/12/2024 | C6: 17819 | D6: EUR m | E6: Amendment to 2025 URD - Half-year report 30/06/2026 | F6: 6 | G6: Key figures and opening of H1-2025 bridge (p.26). | H6: High
A7: NFD_J25 | B7: Net financial debt 30/06/2025 | C7: 20764 | D7: EUR m | E7: Amendment to 2025 URD - Half-year report 30/06/2026 | F7: 26 | H7: High
A8: NFD_D23 | B8: Net financial debt 31/12/2023 | C8: 17903 | D8: EUR m | E8: Amendment to 2023 URD - Half-year report 30/06/2024 | F8: 6 | G8: Key figures, 12/31/2023 column. | H8: High
A9: EBITDA24 | B9: EBITDA FY2024 | C9: 6788 | D9: EUR m | E9: Amendment to 2025 URD - Half-year report 30/06/2026 | F9: 6 | H9: High
A10: EBITDA25 | B10: EBITDA FY2025 | C10: 7050 | D10: EUR m | E10: Amendment to 2025 URD - Half-year report 30/06/2026 | F10: 6 | H10: High
A11: EBITDA_H124 | B11: EBITDA H1 2024 | C11: 3266 | D11: EUR m | E11: Amendment to 2023 URD - Half-year report 30/06/2024 | F11: 6 | G11: As published in 2024 (not restated). | H11: Medium
A12: EBITDA_H125 | B12: EBITDA H1 2025 | C12: 3367 | D12: EUR m | E12: Amendment to 2025 URD - Half-year report 30/06/2026 | F12: 6 | H12: High
A13: EBITDA_H126 | B13: EBITDA H1 2026 | C13: 3552 | D13: EUR m | E13: Amendment to 2025 URD - Half-year report 30/06/2026 | F13: 6 | H13: High
A14: Net free cash flow (Veolia definition: before dividends, financial investments and divestitures)
A15: FCF23 | B15: Net FCF FY2023 | C15: 1143 | D15: EUR m | E15: Amendment to 2023 URD - Half-year report 30/06/2024 | F15: 6 | H15: High
A16: FCF24 | B16: Net FCF FY2024 | C16: 1156 | D16: EUR m | E16: Amendment to 2025 URD - Half-year report 30/06/2026 | F16: 6 | H16: High
A17: FCF25 | B17: Net FCF FY2025 | C17: 1178 | D17: EUR m | E17: Amendment to 2025 URD - Half-year report 30/06/2026 | F17: 6 | H17: High
A18: FCF_H125 | B18: Net FCF H1 2025 | C18: -451 | D18: EUR m | E18: Amendment to 2025 URD - Half-year report 30/06/2026 | F18: 26 | H18: High
A19: FCF_H126 | B19: Net FCF H1 2026 (actual) | C19: -288 | D19: EUR m | E19: Amendment to 2025 URD - Half-year report 30/06/2026 | F19: 26 | H19: High
A20: FCF_g | B20: Net FCF growth per year 2026-27 | C20: =($C$17/$C$15)^(1/2)-1 -> 0.01519514 | D20: % | E20: Derived | G20: Base = 2023-25 CAGR of net FCF (formula). Net FCF has been flat while EBITDA grew: capex and WCR absorb the growth. | H20: Medium
A21: CE_FCF27 | B21: Clean Earth incremental net FCF 2027 | C21: 0 | D21: EUR m | E21: Judgement | G21: EBITDA ~EUR 0.2bn less capex, cash tax and interest on ~EUR 2.8bn of acquisition debt (net FCF is after interest) ~ zero. Replace with Enviri 10-K data. | H21: Low
A22: Shareholder and hybrid outflows
A23: DivPar26 | B23: Parent dividend paid 2026 (on FY2025) | C23: 1099 | D23: EUR m | E23: Amendment to 2025 URD - Half-year report 30/06/2026 | F23: 14 | G23: EUR 1.50/share paid 13/05/2026. | H23: High
A24: DivGrowth | B24: Parent dividend growth 2027 | C24: 0.08 | D24: % | E24: Amendment to 2025 URD - Half-year report 30/06/2026 | F24: 29 | G24: Guidance: dividend growth in line with current EPS, current net income +8% minimum. | H24: Medium
A25: DivMin | B25: Dividends to minorities per year | C25: =$C$26-$C$27 -> 257 | D25: EUR m | E25: Consolidated financial statements 31/12/2025 / Amendment to 2025 URD - Half-year report 30/06/2026 | F25: 7-8 / 6 | G25: FY2025 dividends paid (cash flow statement, 1,280) less parent dividend (H1-2025 key figures, 1,023). | H25: Medium
A26: DivCF25 | B26: Dividends paid FY2025, cash flow statement | C26: 1280 | D26: EUR m | E26: Consolidated financial statements 31/12/2025 | F26: 8 | G26: Parent + minorities. | H26: High
A27: DivPar25 | B27: Parent dividend paid 2025 | C27: 1023 | D27: EUR m | E27: Amendment to 2025 URD - Half-year report 30/06/2026 | F27: 6 | G27: H1-2025 column. NB FY2025 column of the same table shows 895: inconsistency to raise. | H27: Medium
A28: Coup25 | B28: Hybrid coupons paid FY2025 | C28: 121 | D28: EUR m | E28: Consolidated financial statements 31/12/2025 | F28: 8 | H28: High
A29: Hyb25 | B29: Hybrid stock end-2025 | C29: 4100 | D29: EUR m | E29: Consolidated financial statements 31/12/2025 | F29: 74 | G29: Note 9.4.2, 'EUR 4.1 billion'. | H29: High
A30: HybRed | B30: Hybrid redeemed Feb-2026 | C30: 850 | D30: EUR m | E30: Amendment to 2025 URD - Half-year report 30/06/2026 | F30: 14 | G30: Already reclassified as debt at 31/12/2025 (FY25 p.74), so no further NFD impact. | H30: High
A31: DivBridgeH125 | B31: Dividends + coupons in H1-2025 NFD bridge | C31: 1267 | D31: EUR m | E31: Amendment to 2025 URD - Half-year report 30/06/2026 | F31: 26 | G31: Equals 1,173 dividends + 94 coupons (cash flow statement p.36). Gives the H2 seasonal residual. | H31: High
A32: Buyback | B32: Net buyback per year (capital reduction less share issues) | C32: =$C$33-$C$34 -> 84 | D32: EUR m | E32: Consolidated financial statements 31/12/2025 | F32: 8 | G32: Guidance: buyback offsets employee plan dilution. FY2025: 402 - 318. | H32: Medium
A33: CapRed25 | B33: Share capital reduction FY2025 | C33: 402 | D33: EUR m | E33: Consolidated financial statements 31/12/2025 | F33: 8 | H33: High
A34: ShIss25 | B34: Proceeds on issue of shares FY2025 | C34: 318 | D34: EUR m | E34: Consolidated financial statements 31/12/2025 | F34: 8 | H34: High
A35: Disposals (asset rotation)
A36: DispTotal | B36: Disposal programme | C36: 2000 | D36: EUR m | E36: Amendment to 2025 URD - Half-year report 30/06/2026 | F36: 29 | G36: 'EUR 2bn+ disposal program will be delivered by mid 2028.' Gross or net, and whether H1-26 disposals count, is not stated. | H36: Medium
A37: DispShare | B37: Share of programme cashed by 31/12/2027 | C37: 0.75 | D37: % | E37: Judgement | G37: Straight-line to mid-2028 from late 2025 gives ~80%; trimmed for back-loading of large disposals. | H37: Low
A38: DispShareH2 | B38: Of which in H2 2026 | C38: 0.2 | D38: % | E38: Judgement | G38: Only EUR 73m of financial disposals in H1-2026 (p.27). | H38: Low
A39: DispMult | B39: EV/EBITDA multiple of assets sold | C39: 10 | D39: x | E39: Judgement | G39: Each EUR of disposal also removes EBITDA from the ratio's denominator. No published multiple. | H39: Low
A40: EBITDA trajectory
A41: Org26 | B41: Organic EBITDA growth 2026 | C41: 0.055 | D41: % | E41: Amendment to 2025 URD - Half-year report 30/06/2026 | F41: 29 | G41: Guidance +5% to +6%, mid-point. | H41: Medium
A42: FX26 | B42: FX effect on EBITDA 2026 | C42: -0.009 | D42: % | E42: Amendment to 2025 URD - Half-year report 30/06/2026 | F42: 22 | G42: H1-2026 FX effect -0.9%, extrapolated to the year. | H42: Low
A43: Org27 | B43: Organic EBITDA growth 2027 | C43: 0.05 | D43: % | E43: Capstone Project Briefing | F43: 20 | G43: GreenUp 'organic growth of around 5% a year'. | H43: Medium
A44: CE_EV | B44: Clean Earth price | C44: 3040 | D44: USD m | E44: Capstone Project Briefing | F44: 21 | G44: Briefing table. H1-2026 report (p.14) gives USD 2,989m closing price. | H44: Medium
A45: CE_Mult | B45: Clean Earth EV / 2026e EBITDA post-synergies | C45: 9.8 | D45: x | E45: Capstone Project Briefing | F45: 21 | H45: Medium
A46: CE_Syn | B46: Clean Earth run-rate synergies (year 4) | C46: 120 | D46: USD m | E46: Capstone Project Briefing | F46: 21 | H46: Medium
A47: CE_SynPh27 | B47: Share of synergies achieved in 2027 | C47: 0.25 | D47: % | E47: Judgement | G47: Year 1 of 4; H1-2026 report says synergies begin in 2027 (p.13). | H47: Low
A48: USD_EUR | B48: USD per EUR at closing | C48: =2989/2542 -> 1.1758458 | D48: USD/EUR | E48: Amendment to 2025 URD - Half-year report 30/06/2026 | F48: 14 | G48: USD 2,989m = EUR 2,542m on 01/06/2026. | H48: High
A49: CE_Months26 | B49: Clean Earth months consolidated in 2026 | C49: 7 | D49: months | E49: Amendment to 2025 URD - Half-year report 30/06/2026 | F49: 14 | G49: Closed 1 June 2026. | H49: High
A50: EBITDA27_ovr | B50: EBITDA 2027 override (0 = use trajectory) | C50: 0 | D50: EUR m | E50: Capstone Project Briefing | F50: 20 | G50: Set to 8,000 to test the GreenUp target ('at least EUR 8bn in 2027'). | H50: -
A51: Constraint and deal assumptions
A52: Lmax | B52: Leverage cap at 31/12/2027 | C52: 3 | D52: x | E52: Capstone Project Briefing / Amendment to 2023 URD - Half-year report 30/06/2024 | F52: 20 / 12 | G52: GreenUp: 'financial leverage less than or equal to 3x'. | H52: High
A53: Lguid26 | B53: Leverage guidance end-2026 | C53: 3 | D53: x | E53: Amendment to 2025 URD - Half-year report 30/06/2026 | F53: 29 | G53: '3x or slightly above, Clean Earth included' - used as a validation check only. | H53: High
A54: DealMult | B54: EV/EBITDA paid on new acquisitions | C54: 10 | D54: x | E54: Capstone Project Briefing | F54: 21 | G54: Anchored on ~9.8x (Clean Earth) and ~11x (WTS minorities). | H54: Medium
A55: ProForma | B55: Share of acquired EBITDA counted in 2027 ratio | C55: 0 | D55: % | E55: Judgement | G55: 0 = conservative (deal closes late 2027 or ratio uses reported EBITDA). Ask Veolia whether the covenant/guidance ratio is pro forma. | H55: Low
A56: FX_H2 | B56: FX / other on NFD, H2 2026 | C56: 0 | D56: EUR m | E56: Judgement | G56: H1-2026: -260 (p.26). USD share of debt has risen with Clean Earth. | H56: Low
A57: FX_27 | B57: FX / other on NFD, 2027 | C57: 0 | D57: EUR m | E57: Judgement | G57: Positive = debt increases. | H57: Low
A58: Liquidity (for the cash-availability formula)
A59: Cash_J26 | B59: Cash, cash equivalents and liquid assets 30/06/2026 | C59: 9332 | D59: EUR m | E59: Amendment to 2025 URD - Half-year report 30/06/2026 | F59: 14 | G59: 'Cash stands at EUR 9,332 million'. Equals 7,288 cash + 2,044 liquid assets (p.28). | H59: High
A60: Undrawn_J26 | B60: Undrawn committed credit lines 30/06/2026 | C60: =4500+1373 -> 5873 | D60: EUR m | E60: Amendment to 2025 URD - Half-year report 30/06/2026 | F60: 14 | G60: Syndicated loan 4,500 (matures 2030) + bilateral lines 1,373. Counted as 'permitted borrowing'; new bond issues are not counted. | H60: High
A61: CurDebt_J26 | B61: Current debt incl. overdrafts 30/06/2026 (due within 12 months) | C61: 11374 | D61: EUR m | E61: Amendment to 2025 URD - Half-year report 30/06/2026 | F61: 28 | G61: Mostly commercial paper and bonds due by June 2027. Treated as repaid, not rolled over (prudent). | H61: High
A62: Mat27 | B62: Contractual debt flows due in calendar 2027 | C62: 3891 | D62: EUR m | E62: Consolidated financial statements 31/12/2025 | F62: 66 | G62: Undiscounted, incl. interest, at 31/12/2025. | H62: Medium
A63: Mat27H2 | B63: Share of 2027 flows falling in H2 2027 (not already in current debt) | C63: 0.5 | D63: % | E63: Judgement | G63: Timing within 2027 not published. | H63: Low
A64: MinCash | B64: Minimum cash reserve | C64: 2000 | D64: EUR m | E64: Judgement | G64: No published floor. Veolia has held EUR 7-10bn of cash at every reporting date; EUR 2bn is a working floor to debate. | H64: Low
A65: Committed | B65: Investments already committed, not yet paid | C65: 0 | D65: EUR m | E65: Consolidated financial statements 31/12/2025 | F65: 18 | G65: The only securities purchase commitment at 31/12/2025 was Clean Earth, paid June 2026. Industrial capex is already inside net FCF. | H65: Medium
A66: Rating cross-check (unverified - read the PDF before using)
A67: Moody_Fcst27 | B67: Moody's forecast FFO / net debt 2027 | C67: 0.195 | D67: % | E67: Moody's Credit Opinion 04/05/2026 (veolia.com) - NOT YET VERIFIED | G67: Search-result extract only; the PDF could not be downloaded from this environment. | H67: Low
A68: Moody_Trig | B68: Moody's downgrade threshold FFO / net debt ('below the high teens') | C68: 0.18 | D68: % | E68: Moody's Credit Opinion 04/05/2026 (veolia.com) - NOT YET VERIFIED | G68: 'High teens' read as 18%. Agency wording, not a number: judgement. | H68: Low
A70: Legend: blue = sourced input; black = derived from other inputs; yellow fill = judgement call the group must defend.

Sheet Spent
A1: Period | B1: Item | C1: Gross acquisitions (EUR m) | D1: Disposals (EUR m) | E1: Basis | F1: Source | G1: PDF page | H1: Booster?
A2: A. Named deals (net financial investment as published)
A3: 2024 | B3: Friedrich Hofmann (recycling, Germany) | C3: 315 | E3: Deal price | F3: Amendment to 2023 URD - Half-year report 30/06/2024 | G3: 29 | H3: No
A4: 2025 | B4: Danubius (electricity flexibility, Hungary) | C4: 271 | E4: Net financial investment | F4: Consolidated financial statements 31/12/2025 | G4: 17 | H4: Yes
A5: 2025 | B5: WTS 30% minority buy-out from CDPQ | C5: 1500 | E5: Purchase price (USD 1.75bn) | F5: Consolidated financial statements 31/12/2025 | G5: 17 | H5: Yes
A6: 2025 | B6: US hazardous waste tuck-ins + Chameleon | C6: 247 | E6: Net financial investment | F6: Consolidated financial statements 31/12/2025 | G6: 17 | H6: Yes
A7: 2025 | B7: Zeeklite (hazardous waste, Japan) | C7: 85 | E7: Net financial investment | F7: Consolidated financial statements 31/12/2025 | G7: 17 | H7: Yes
A8: H1-26 | B8: Enviropacific Services (Australia) | C8: 137 | E8: Net financial investment | F8: Amendment to 2025 URD - Half-year report 30/06/2026 | G8: 27 | H8: Yes
A9: H1-26 | B9: Clean Earth (US) incl. IFRS 16 debt and costs | C9: 2778 | E9: Net financial investment | F9: Amendment to 2025 URD - Half-year report 30/06/2026 | G9: 27 | H9: Yes
A10: B. All financial flows (cash flow statement basis, comparable across years)
A11: 2024 | B11: Purchases of investments + NCI partial purchases / disposals + NCI sales | C11: =482+32 -> 514 | D11: =949+1 -> 950 | E11: Cash flow statement | F11: Consolidated financial statements 31/12/2025 | G11: 7-8
A12: 2025 | B12: Purchases of investments + NCI partial purchases / disposals + NCI sales | C12: =702+1563 -> 2265 | D12: =59+37 -> 96 | E12: Cash flow statement | F12: Consolidated financial statements 31/12/2025 | G12: 7-8
A13: H1-26 | B13: Financial acquisitions / financial disposals (Veolia NFI basis) | C13: 2942 | D13: 73 | E13: Net financial investments | F13: Amendment to 2025 URD - Half-year report 30/06/2026 | G13: 27
A14: 2023 | B14: FY2023 not covered by the documents loaded (only H1-2023: -241 / +183) | E14: GAP | F14: Amendment to 2023 URD - Half-year report 30/06/2024 | G14: 29
B16: Envelope announced (GreenUp 'EUR 4bn in growth investments') | C16: =4000 -> 4000 | E16: Briefing p.20 says 'acquisitions over 2023-2027'; the 2024 GreenUp text (H1-24 p.12) says '2024-2027 growth investments'. The scope is not the same thing.
B17: Named deals, gross | C17: =SUM(C3:C9) -> 5333
B18: Named deals in boosters | C18: =SUMIF(H3:H9,"Yes",C3:C9) -> 5018 | E18: Envelope says EUR 2bn prioritised for boosters.
B19: All financial acquisitions 2024-H1-26, gross | C19: =SUM(C11:C13) -> 5721 | E19: Mixes CF-statement basis (2024-25) and NFI basis (H1-26): conservative order of magnitude.
B20: All financial disposals 2024-H1-26 | C20: =SUM(D11:D13) -> 1119 | E20: 2024 includes SADE and Haikou (pre-programme).
B21: All financial acquisitions, net of disposals | C21: =C19-C20 -> 4602
B22: Envelope remaining - gross reading | C22: =C16-C19 -> -1721 | E22: Negative = envelope already exceeded.
B23: Envelope remaining - net reading | C23: =C16-C21 -> -602

Sheet Start
A1: Metric (EUR m) | B1: Dec-24 | C1: Jun-25 | D1: Dec-25 | E1: Jun-26 | F1: Note
A2: Net financial debt (Veolia definition) | B2: =Inputs!$C$6 -> 17819 | C2: =Inputs!$C$7 -> 20764 | D2: =Inputs!$C$4 -> 19657 | E2: =Inputs!$C$3 -> 24548 | F2: Dec-25 statutory note shows 19,821: the 164 gap must be explained in the report.
A3: EBITDA - fiscal year / LTM | B3: =Inputs!$C$9 -> 6788 | C3: =Inputs!$C$9-Inputs!$C$11+Inputs!$C$12 -> 6889 | D3: =Inputs!$C$10 -> 7050 | E3: =Inputs!$C$10-Inputs!$C$12+Inputs!$C$13 -> 7235 | F3: June columns = last twelve months (FY - previous H1 + current H1).
A4: Leverage NFD / EBITDA | B4: =B2/B3 -> 2.6250737 | C4: =C2/C3 -> 3.0140804 | D4: =D2/D3 -> 2.788227 | E4: =E2/E3 -> 3.3929509 | F4: June ratios are seasonally high (dividend and WCR outflows land in H1) - do not compare with the year-end 3x cap.
A7: Debt maturity profile at 31/12/2025 (undiscounted contractual flows incl. interest)
A8: Line (EUR m) | B8: 2026 | C8: 2027 | D8: 2028 | E8: 2029 | F8: Source
A9: Bond issues | B9: 1924 | C9: 3043 | D9: 2447 | E9: 1781 | F9: Consolidated financial statements 31/12/2025, PDF p.66
A10: Other liabilities and overdrafts | B10: 7219 | C10: 465 | D10: 728 | E10: 302 | F10: Consolidated financial statements 31/12/2025, PDF p.66
A11: IFRS 16 lease debt | B11: 499 | C11: 384 | D11: 317 | E11: 198 | F11: Consolidated financial statements 31/12/2025, PDF p.66
A12: Total | B12: =SUM(B9:B11) -> 9642 | C12: =SUM(C9:C11) -> 3892 | D12: =SUM(D9:D11) -> 3492 | E12: =SUM(E9:E11) -> 2281
A14: Liquidity and rating at 30/06/2026
A15: Total liquid assets | B15: 15205 | F15: H1-26 p.28
A16: Current debt incl. overdrafts | B16: 11374 | F16: H1-26 p.28
A17: Net liquidity | B17: =B15-B16 -> 3831 | F17: Matches 3,831 published (p.14)
A18: 2026 bond issues (Jan EUR 2.5bn + Apr EUR 1.0bn + Jun EUR 0.4bn convertible) | B18: =2500+1000+400 -> 3900 | F18: H1-26 p.14: 2027 maturities pre-financed in part
A19: Rating | B19: BBB / Baa1, stable | F19: S&P 27/04/2026, Moody's 04/05/2026 (H1-26 p.14)
A20: Bond/bank documentation financial covenants at parent | B20: None | F20: FY25 p.67: the 3x is a public commitment, not a covenant - the binding constraint is the rating

Sheet Engine
A1: Engine - one column per case (EUR m unless stated)
A2: Case | B2: Base | C2: GreenUp met | D2: Downside | E2: Upside | F2: EBITDA 2027 level - low | G2: EBITDA 2027 level - high | H2: Organic EBITDA growth 2027 - low | I2: Organic EBITDA growth 2027 - high | J2: Net FCF growth p.a. - low | K2: Net FCF growth p.a. - high | L2: Disposals cashed by end-2027 - low | M2: Disposals cashed by end-2027 - high | N2: Multiple on assets sold - low | O2: Multiple on assets sold - high | P2: Parent dividend growth 2027 - low | Q2: Parent dividend growth 2027 - high | R2: FX / other on NFD 2027 (EUR m) - low | S2: FX / other on NFD 2027 (EUR m) - high | T2: Acquired EBITDA in 2027 ratio - low | U2: Acquired EBITDA in 2027 ratio - high | V2: Multiple paid on acquisitions - low | W2: Multiple paid on acquisitions - high | X2: Clean Earth EV/EBITDA (sets its EBITDA) - low | Y2: Clean Earth EV/EBITDA (sets its EBITDA) - high | Z2: Leverage cap - low | AA2: Leverage cap - high
A3: Description | B3: Trajectory | C3: EBITDA 2027 = EUR 8.0bn | D3: Slower growth, half the disposals, USD/FX drag | E3: Full disposals by 2027, pro forma ratio | F3: Sensitivity | G3: Sensitivity | H3: Sensitivity | I3: Sensitivity | J3: Sensitivity | K3: Sensitivity | L3: Sensitivity | M3: Sensitivity | N3: Sensitivity | O3: Sensitivity | P3: Sensitivity | Q3: Sensitivity | R3: Sensitivity | S3: Sensitivity | T3: Sensitivity | U3: Sensitivity | V3: Sensitivity | W3: Sensitivity | X3: Sensitivity | Y3: Sensitivity | Z3: Sensitivity | AA3: Sensitivity
A4: Drivers (green = linked to Inputs, blue = case override)
A5: Net financial debt 30/06/2026 | B5: =Inputs!$C$3 -> 24548 | C5: =Inputs!$C$3 -> 24548 | D5: =Inputs!$C$3 -> 24548 | E5: =Inputs!$C$3 -> 24548 | F5: =Inputs!$C$3 -> 24548 | G5: =Inputs!$C$3 -> 24548 | H5: =Inputs!$C$3 -> 24548 | I5: =Inputs!$C$3 -> 24548 | ... AA5: =Inputs!$C$3 -> 24548
A6: Net FCF FY2025 | B6: =Inputs!$C$17 -> 1178 | C6: =Inputs!$C$17 -> 1178 | D6: =Inputs!$C$17 -> 1178 | E6: =Inputs!$C$17 -> 1178 | F6: =Inputs!$C$17 -> 1178 | G6: =Inputs!$C$17 -> 1178 | H6: =Inputs!$C$17 -> 1178 | I6: =Inputs!$C$17 -> 1178 | ... AA6: =Inputs!$C$17 -> 1178
A7: Net FCF growth per year 2026-27 | B7: =Inputs!$C$20 -> 0.01519514 | C7: =Inputs!$C$20 -> 0.01519514 | D7: 0 | E7: =Inputs!$C$20 -> 0.01519514 | F7: =Inputs!$C$20 -> 0.01519514 | G7: =Inputs!$C$20 -> 0.01519514 | H7: =Inputs!$C$20 -> 0.01519514 | I7: =Inputs!$C$20 -> 0.01519514 | J7: -0.03 | K7: 0.05 | L7: =Inputs!$C$20 -> 0.01519514 | M7: =Inputs!$C$20 -> 0.01519514 | N7: =Inputs!$C$20 -> 0.01519514 | O7: =Inputs!$C$20 -> 0.01519514 | P7: =Inputs!$C$20 -> 0.01519514 | Q7: =Inputs!$C$20 -> 0.01519514 | R7: =Inputs!$C$20 -> 0.01519514 | S7: =Inputs!$C$20 -> 0.01519514 | ... AA7: =Inputs!$C$20 -> 0.01519514
A8: Net FCF H1 2026 (actual) | B8: =Inputs!$C$19 -> -288 | C8: =Inputs!$C$19 -> -288 | D8: =Inputs!$C$19 -> -288 | E8: =Inputs!$C$19 -> -288 | F8: =Inputs!$C$19 -> -288 | G8: =Inputs!$C$19 -> -288 | H8: =Inputs!$C$19 -> -288 | I8: =Inputs!$C$19 -> -288 | ... AA8: =Inputs!$C$19 -> -288
A9: Clean Earth incremental net FCF 2027 | B9: =Inputs!$C$21 -> 0 | C9: =Inputs!$C$21 -> 0 | D9: =Inputs!$C$21 -> 0 | E9: =Inputs!$C$21 -> 0 | F9: =Inputs!$C$21 -> 0 | G9: =Inputs!$C$21 -> 0 | H9: =Inputs!$C$21 -> 0 | I9: =Inputs!$C$21 -> 0 | ... AA9: =Inputs!$C$21 -> 0
A10: Parent dividend paid 2026 (on FY2025) | B10: =Inputs!$C$23 -> 1099 | C10: =Inputs!$C$23 -> 1099 | D10: =Inputs!$C$23 -> 1099 | E10: =Inputs!$C$23 -> 1099 | F10: =Inputs!$C$23 -> 1099 | G10: =Inputs!$C$23 -> 1099 | H10: =Inputs!$C$23 -> 1099 | I10: =Inputs!$C$23 -> 1099 | ... AA10: =Inputs!$C$23 -> 1099
A11: Parent dividend growth 2027 | B11: =Inputs!$C$24 -> 0.08 | C11: =Inputs!$C$24 -> 0.08 | D11: =Inputs!$C$24 -> 0.08 | E11: =Inputs!$C$24 -> 0.08 | F11: =Inputs!$C$24 -> 0.08 | G11: =Inputs!$C$24 -> 0.08 | H11: =Inputs!$C$24 -> 0.08 | I11: =Inputs!$C$24 -> 0.08 | ... O11: =Inputs!$C$24 -> 0.08 | P11: 0.04 | Q11: 0.1 | R11: =Inputs!$C$24 -> 0.08 | S11: =Inputs!$C$24 -> 0.08 | T11: =Inputs!$C$24 -> 0.08 | U11: =Inputs!$C$24 -> 0.08 | V11: =Inputs!$C$24 -> 0.08 | W11: =Inputs!$C$24 -> 0.08 | X11: =Inputs!$C$24 -> 0.08 | Y11: =Inputs!$C$24 -> 0.08 | ... AA11: =Inputs!$C$24 -> 0.08
A12: Dividends to minorities per year | B12: =Inputs!$C$25 -> 257 | C12: =Inputs!$C$25 -> 257 | D12: =Inputs!$C$25 -> 257 | E12: =Inputs!$C$25 -> 257 | F12: =Inputs!$C$25 -> 257 | G12: =Inputs!$C$25 -> 257 | H12: =Inputs!$C$25 -> 257 | I12: =Inputs!$C$25 -> 257 | ... AA12: =Inputs!$C$25 -> 257
A13: Dividends paid FY2025, cash flow statement | B13: =Inputs!$C$26 -> 1280 | C13: =Inputs!$C$26 -> 1280 | D13: =Inputs!$C$26 -> 1280 | E13: =Inputs!$C$26 -> 1280 | F13: =Inputs!$C$26 -> 1280 | G13: =Inputs!$C$26 -> 1280 | H13: =Inputs!$C$26 -> 1280 | I13: =Inputs!$C$26 -> 1280 | ... AA13: =Inputs!$C$26 -> 1280
A14: Hybrid coupons paid FY2025 | B14: =Inputs!$C$28 -> 121 | C14: =Inputs!$C$28 -> 121 | D14: =Inputs!$C$28 -> 121 | E14: =Inputs!$C$28 -> 121 | F14: =Inputs!$C$28 -> 121 | G14: =Inputs!$C$28 -> 121 | H14: =Inputs!$C$28 -> 121 | I14: =Inputs!$C$28 -> 121 | ... AA14: =Inputs!$C$28 -> 121
A15: Hybrid stock end-2025 | B15: =Inputs!$C$29 -> 4100 | C15: =Inputs!$C$29 -> 4100 | D15: =Inputs!$C$29 -> 4100 | E15: =Inputs!$C$29 -> 4100 | F15: =Inputs!$C$29 -> 4100 | G15: =Inputs!$C$29 -> 4100 | H15: =Inputs!$C$29 -> 4100 | I15: =Inputs!$C$29 -> 4100 | ... AA15: =Inputs!$C$29 -> 4100
A16: Hybrid redeemed Feb-2026 | B16: =Inputs!$C$30 -> 850 | C16: =Inputs!$C$30 -> 850 | D16: =Inputs!$C$30 -> 850 | E16: =Inputs!$C$30 -> 850 | F16: =Inputs!$C$30 -> 850 | G16: =Inputs!$C$30 -> 850 | H16: =Inputs!$C$30 -> 850 | I16: =Inputs!$C$30 -> 850 | ... AA16: =Inputs!$C$30 -> 850
A17: Dividends + coupons in H1-2025 NFD bridge | B17: =Inputs!$C$31 -> 1267 | C17: =Inputs!$C$31 -> 1267 | D17: =Inputs!$C$31 -> 1267 | E17: =Inputs!$C$31 -> 1267 | F17: =Inputs!$C$31 -> 1267 | G17: =Inputs!$C$31 -> 1267 | H17: =Inputs!$C$31 -> 1267 | I17: =Inputs!$C$31 -> 1267 | ... AA17: =Inputs!$C$31 -> 1267
A18: Net buyback per year (capital reduction less share issues) | B18: =Inputs!$C$32 -> 84 | C18: =Inputs!$C$32 -> 84 | D18: =Inputs!$C$32 -> 84 | E18: =Inputs!$C$32 -> 84 | F18: =Inputs!$C$32 -> 84 | G18: =Inputs!$C$32 -> 84 | H18: =Inputs!$C$32 -> 84 | I18: =Inputs!$C$32 -> 84 | ... AA18: =Inputs!$C$32 -> 84
A19: Disposal programme | B19: =Inputs!$C$36 -> 2000 | C19: =Inputs!$C$36 -> 2000 | D19: =Inputs!$C$36 -> 2000 | E19: =Inputs!$C$36 -> 2000 | F19: =Inputs!$C$36 -> 2000 | G19: =Inputs!$C$36 -> 2000 | H19: =Inputs!$C$36 -> 2000 | I19: =Inputs!$C$36 -> 2000 | ... AA19: =Inputs!$C$36 -> 2000
A20: Share of programme cashed by 31/12/2027 | B20: =Inputs!$C$37 -> 0.75 | C20: =Inputs!$C$37 -> 0.75 | D20: 0.5 | E20: 1 | F20: =Inputs!$C$37 -> 0.75 | G20: =Inputs!$C$37 -> 0.75 | H20: =Inputs!$C$37 -> 0.75 | I20: =Inputs!$C$37 -> 0.75 | J20: =Inputs!$C$37 -> 0.75 | K20: =Inputs!$C$37 -> 0.75 | L20: 0.5 | M20: 1 | N20: =Inputs!$C$37 -> 0.75 | O20: =Inputs!$C$37 -> 0.75 | P20: =Inputs!$C$37 -> 0.75 | Q20: =Inputs!$C$37 -> 0.75 | R20: =Inputs!$C$37 -> 0.75 | S20: =Inputs!$C$37 -> 0.75 | T20: =Inputs!$C$37 -> 0.75 | U20: =Inputs!$C$37 -> 0.75 | ... AA20: =Inputs!$C$37 -> 0.75
A21: Of which in H2 2026 | B21: =Inputs!$C$38 -> 0.2 | C21: =Inputs!$C$38 -> 0.2 | D21: =Inputs!$C$38 -> 0.2 | E21: =Inputs!$C$38 -> 0.2 | F21: =Inputs!$C$38 -> 0.2 | G21: =Inputs!$C$38 -> 0.2 | H21: =Inputs!$C$38 -> 0.2 | I21: =Inputs!$C$38 -> 0.2 | ... AA21: =Inputs!$C$38 -> 0.2
A22: EV/EBITDA multiple of assets sold | B22: =Inputs!$C$39 -> 10 | C22: =Inputs!$C$39 -> 10 | D22: 8 | E22: 12 | F22: =Inputs!$C$39 -> 10 | G22: =Inputs!$C$39 -> 10 | H22: =Inputs!$C$39 -> 10 | I22: =Inputs!$C$39 -> 10 | J22: =Inputs!$C$39 -> 10 | K22: =Inputs!$C$39 -> 10 | L22: =Inputs!$C$39 -> 10 | M22: =Inputs!$C$39 -> 10 | N22: 7 | O22: 13 | P22: =Inputs!$C$39 -> 10 | Q22: =Inputs!$C$39 -> 10 | R22: =Inputs!$C$39 -> 10 | S22: =Inputs!$C$39 -> 10 | T22: =Inputs!$C$39 -> 10 | U22: =Inputs!$C$39 -> 10 | V22: =Inputs!$C$39 -> 10 | W22: =Inputs!$C$39 -> 10 | ... AA22: =Inputs!$C$39 -> 10
A23: Organic EBITDA growth 2026 | B23: =Inputs!$C$41 -> 0.055 | C23: =Inputs!$C$41 -> 0.055 | D23: =Inputs!$C$41 -> 0.055 | E23: =Inputs!$C$41 -> 0.055 | F23: =Inputs!$C$41 -> 0.055 | G23: =Inputs!$C$41 -> 0.055 | H23: =Inputs!$C$41 -> 0.055 | I23: =Inputs!$C$41 -> 0.055 | ... AA23: =Inputs!$C$41 -> 0.055
A24: FX effect on EBITDA 2026 | B24: =Inputs!$C$42 -> -0.009 | C24: =Inputs!$C$42 -> -0.009 | D24: =Inputs!$C$42 -> -0.009 | E24: =Inputs!$C$42 -> -0.009 | F24: =Inputs!$C$42 -> -0.009 | G24: =Inputs!$C$42 -> -0.009 | H24: =Inputs!$C$42 -> -0.009 | I24: =Inputs!$C$42 -> -0.009 | ... AA24: =Inputs!$C$42 -> -0.009
A25: Organic EBITDA growth 2027 | B25: =Inputs!$C$43 -> 0.05 | C25: =Inputs!$C$43 -> 0.05 | D25: 0.04 | E25: 0.06 | F25: =Inputs!$C$43 -> 0.05 | G25: =Inputs!$C$43 -> 0.05 | H25: 0.04 | I25: 0.06 | J25: =Inputs!$C$43 -> 0.05 | K25: =Inputs!$C$43 -> 0.05 | L25: =Inputs!$C$43 -> 0.05 | M25: =Inputs!$C$43 -> 0.05 | N25: =Inputs!$C$43 -> 0.05 | O25: =Inputs!$C$43 -> 0.05 | P25: =Inputs!$C$43 -> 0.05 | Q25: =Inputs!$C$43 -> 0.05 | ... AA25: =Inputs!$C$43 -> 0.05
A26: EBITDA FY2025 | B26: =Inputs!$C$10 -> 7050 | C26: =Inputs!$C$10 -> 7050 | D26: =Inputs!$C$10 -> 7050 | E26: =Inputs!$C$10 -> 7050 | F26: =Inputs!$C$10 -> 7050 | G26: =Inputs!$C$10 -> 7050 | H26: =Inputs!$C$10 -> 7050 | I26: =Inputs!$C$10 -> 7050 | ... AA26: =Inputs!$C$10 -> 7050
A27: Clean Earth price | B27: =Inputs!$C$44 -> 3040 | C27: =Inputs!$C$44 -> 3040 | D27: =Inputs!$C$44 -> 3040 | E27: =Inputs!$C$44 -> 3040 | F27: =Inputs!$C$44 -> 3040 | G27: =Inputs!$C$44 -> 3040 | H27: =Inputs!$C$44 -> 3040 | I27: =Inputs!$C$44 -> 3040 | ... AA27: =Inputs!$C$44 -> 3040
A28: Clean Earth EV / 2026e EBITDA post-synergies | B28: =Inputs!$C$45 -> 9.8 | C28: =Inputs!$C$45 -> 9.8 | D28: =Inputs!$C$45 -> 9.8 | E28: =Inputs!$C$45 -> 9.8 | F28: =Inputs!$C$45 -> 9.8 | G28: =Inputs!$C$45 -> 9.8 | H28: =Inputs!$C$45 -> 9.8 | I28: =Inputs!$C$45 -> 9.8 | ... W28: =Inputs!$C$45 -> 9.8 | X28: 11.5 | Y28: 8.5 | Z28: =Inputs!$C$45 -> 9.8 | AA28: =Inputs!$C$45 -> 9.8
A29: Clean Earth run-rate synergies (year 4) | B29: =Inputs!$C$46 -> 120 | C29: =Inputs!$C$46 -> 120 | D29: =Inputs!$C$46 -> 120 | E29: =Inputs!$C$46 -> 120 | F29: =Inputs!$C$46 -> 120 | G29: =Inputs!$C$46 -> 120 | H29: =Inputs!$C$46 -> 120 | I29: =Inputs!$C$46 -> 120 | ... AA29: =Inputs!$C$46 -> 120
A30: Share of synergies achieved in 2027 | B30: =Inputs!$C$47 -> 0.25 | C30: =Inputs!$C$47 -> 0.25 | D30: =Inputs!$C$47 -> 0.25 | E30: =Inputs!$C$47 -> 0.25 | F30: =Inputs!$C$47 -> 0.25 | G30: =Inputs!$C$47 -> 0.25 | H30: =Inputs!$C$47 -> 0.25 | I30: =Inputs!$C$47 -> 0.25 | ... AA30: =Inputs!$C$47 -> 0.25
A31: USD per EUR at closing | B31: =Inputs!$C$48 -> 1.1758458 | C31: =Inputs!$C$48 -> 1.1758458 | D31: =Inputs!$C$48 -> 1.1758458 | E31: =Inputs!$C$48 -> 1.1758458 | F31: =Inputs!$C$48 -> 1.1758458 | G31: =Inputs!$C$48 -> 1.1758458 | H31: =Inputs!$C$48 -> 1.1758458 | I31: =Inputs!$C$48 -> 1.1758458 | ... AA31: =Inputs!$C$48 -> 1.1758458
A32: Clean Earth months consolidated in 2026 | B32: =Inputs!$C$49 -> 7 | C32: =Inputs!$C$49 -> 7 | D32: =Inputs!$C$49 -> 7 | E32: =Inputs!$C$49 -> 7 | F32: =Inputs!$C$49 -> 7 | G32: =Inputs!$C$49 -> 7 | H32: =Inputs!$C$49 -> 7 | I32: =Inputs!$C$49 -> 7 | ... AA32: =Inputs!$C$49 -> 7
A33: EBITDA 2027 override (0 = use trajectory) | B33: =Inputs!$C$50 -> 0 | C33: 8000 | D33: =Inputs!$C$50 -> 0 | E33: =Inputs!$C$50 -> 0 | F33: 7750 | G33: 8250 | H33: =Inputs!$C$50 -> 0 | I33: =Inputs!$C$50 -> 0 | J33: =Inputs!$C$50 -> 0 | K33: =Inputs!$C$50 -> 0 | L33: =Inputs!$C$50 -> 0 | M33: =Inputs!$C$50 -> 0 | N33: =Inputs!$C$50 -> 0 | O33: =Inputs!$C$50 -> 0 | ... AA33: =Inputs!$C$50 -> 0
A34: Leverage cap at 31/12/2027 | B34: =Inputs!$C$52 -> 3 | C34: =Inputs!$C$52 -> 3 | D34: =Inputs!$C$52 -> 3 | E34: =Inputs!$C$52 -> 3 | F34: =Inputs!$C$52 -> 3 | G34: =Inputs!$C$52 -> 3 | H34: =Inputs!$C$52 -> 3 | I34: =Inputs!$C$52 -> 3 | ... Y34: =Inputs!$C$52 -> 3 | Z34: 2.9 | AA34: 3.1
A35: Leverage guidance end-2026 | B35: =Inputs!$C$53 -> 3 | C35: =Inputs!$C$53 -> 3 | D35: =Inputs!$C$53 -> 3 | E35: =Inputs!$C$53 -> 3 | F35: =Inputs!$C$53 -> 3 | G35: =Inputs!$C$53 -> 3 | H35: =Inputs!$C$53 -> 3 | I35: =Inputs!$C$53 -> 3 | ... AA35: =Inputs!$C$53 -> 3
A36: EV/EBITDA paid on new acquisitions | B36: =Inputs!$C$54 -> 10 | C36: =Inputs!$C$54 -> 10 | D36: =Inputs!$C$54 -> 10 | E36: =Inputs!$C$54 -> 10 | F36: =Inputs!$C$54 -> 10 | G36: =Inputs!$C$54 -> 10 | H36: =Inputs!$C$54 -> 10 | I36: =Inputs!$C$54 -> 10 | ... U36: =Inputs!$C$54 -> 10 | V36: 8 | W36: 12 | X36: =Inputs!$C$54 -> 10 | Y36: =Inputs!$C$54 -> 10 | Z36: =Inputs!$C$54 -> 10 | AA36: =Inputs!$C$54 -> 10
A37: Share of acquired EBITDA counted in 2027 ratio | B37: =Inputs!$C$55 -> 0 | C37: =Inputs!$C$55 -> 0 | D37: =Inputs!$C$55 -> 0 | E37: 1 | F37: =Inputs!$C$55 -> 0 | G37: =Inputs!$C$55 -> 0 | H37: =Inputs!$C$55 -> 0 | I37: =Inputs!$C$55 -> 0 | J37: =Inputs!$C$55 -> 0 | K37: =Inputs!$C$55 -> 0 | L37: =Inputs!$C$55 -> 0 | M37: =Inputs!$C$55 -> 0 | ... S37: =Inputs!$C$55 -> 0 | T37: 0 | U37: 1 | V37: =Inputs!$C$55 -> 0 | W37: =Inputs!$C$55 -> 0 | X37: =Inputs!$C$55 -> 0 | Y37: =Inputs!$C$55 -> 0 | Z37: =Inputs!$C$55 -> 0 | AA37: =Inputs!$C$55 -> 0
A38: FX / other on NFD, H2 2026 | B38: =Inputs!$C$56 -> 0 | C38: =Inputs!$C$56 -> 0 | D38: =Inputs!$C$56 -> 0 | E38: =Inputs!$C$56 -> 0 | F38: =Inputs!$C$56 -> 0 | G38: =Inputs!$C$56 -> 0 | H38: =Inputs!$C$56 -> 0 | I38: =Inputs!$C$56 -> 0 | ... AA38: =Inputs!$C$56 -> 0
A39: FX / other on NFD, 2027 | B39: =Inputs!$C$57 -> 0 | C39: =Inputs!$C$57 -> 0 | D39: 300 | E39: =Inputs!$C$57 -> 0 | F39: =Inputs!$C$57 -> 0 | G39: =Inputs!$C$57 -> 0 | H39: =Inputs!$C$57 -> 0 | I39: =Inputs!$C$57 -> 0 | J39: =Inputs!$C$57 -> 0 | K39: =Inputs!$C$57 -> 0 | L39: =Inputs!$C$57 -> 0 | ... Q39: =Inputs!$C$57 -> 0 | R39: 400 | S39: -400 | T39: =Inputs!$C$57 -> 0 | U39: =Inputs!$C$57 -> 0 | V39: =Inputs!$C$57 -> 0 | W39: =Inputs!$C$57 -> 0 | X39: =Inputs!$C$57 -> 0 | Y39: =Inputs!$C$57 -> 0 | Z39: =Inputs!$C$57 -> 0 | AA39: =Inputs!$C$57 -> 0
A41: Calculation
A42: Clean Earth EBITDA 2026e, full year (EUR m) | B42: =(B27/B28-B29)/B31 -> 161.75938 | C42: =(C27/C28-C29)/C31 -> 161.75938 | D42: =(D27/D28-D29)/D31 -> 161.75938 | E42: =(E27/E28-E29)/E31 -> 161.75938 | F42: =(F27/F28-F29)/F31 -> 161.75938 | G42: =(G27/G28-G29)/G31 -> 161.75938 | H42: =(H27/H28-H29)/H31 -> 161.75938 | I42: =(I27/I28-I29)/I31 -> 161.75938 | ... AA42: =(AA27/AA28-AA29)/AA31 -> 161.75938
A43: Clean Earth synergies in 2027 (EUR m) | B43: =B29*B30/B31 -> 25.51355 | C43: =C29*C30/C31 -> 25.51355 | D43: =D29*D30/D31 -> 25.51355 | E43: =E29*E30/E31 -> 25.51355 | F43: =F29*F30/F31 -> 25.51355 | G43: =G29*G30/G31 -> 25.51355 | H43: =H29*H30/H31 -> 25.51355 | I43: =I29*I30/I31 -> 25.51355 | ... AA43: =AA29*AA30/AA31 -> 25.51355
A44: Net FCF FY2026e | B44: =B6*(1+B7) -> 1195.8999 | C44: =C6*(1+C7) -> 1195.8999 | D44: =D6*(1+D7) -> 1178 | E44: =E6*(1+E7) -> 1195.8999 | F44: =F6*(1+F7) -> 1195.8999 | G44: =G6*(1+G7) -> 1195.8999 | H44: =H6*(1+H7) -> 1195.8999 | I44: =I6*(1+I7) -> 1195.8999 | ... AA44: =AA6*(1+AA7) -> 1195.8999
A45: Net FCF H2 2026e (FY less H1 actual) | B45: =B44-B8 -> 1483.8999 | C45: =C44-C8 -> 1483.8999 | D45: =D44-D8 -> 1466 | E45: =E44-E8 -> 1483.8999 | F45: =F44-F8 -> 1483.8999 | G45: =G44-G8 -> 1483.8999 | H45: =H44-H8 -> 1483.8999 | I45: =I44-I8 -> 1483.8999 | ... AA45: =AA44-AA8 -> 1483.8999
A46: Net FCF FY2027e | B46: =B44*(1+B7)+B9 -> 1214.0717 | C46: =C44*(1+C7)+C9 -> 1214.0717 | D46: =D44*(1+D7)+D9 -> 1178 | E46: =E44*(1+E7)+E9 -> 1214.0717 | F46: =F44*(1+F7)+F9 -> 1214.0717 | G46: =G44*(1+G7)+G9 -> 1214.0717 | H46: =H44*(1+H7)+H9 -> 1214.0717 | I46: =I44*(1+I7)+I9 -> 1214.0717 | ... AA46: =AA44*(1+AA7)+AA9 -> 1214.0717
A47: Dividends + coupons H2 2026 (FY25 residual) | B47: =B13+B14-B17 -> 134 | C47: =C13+C14-C17 -> 134 | D47: =D13+D14-D17 -> 134 | E47: =E13+E14-E17 -> 134 | F47: =F13+F14-F17 -> 134 | G47: =G13+G14-G17 -> 134 | H47: =H13+H14-H17 -> 134 | I47: =I13+I14-I17 -> 134 | ... AA47: =AA13+AA14-AA17 -> 134
A48: Hybrid coupons 2027 (after Feb-26 redemption) | B48: =B14*(B15-B16)/B15 -> 95.914634 | C48: =C14*(C15-C16)/C15 -> 95.914634 | D48: =D14*(D15-D16)/D15 -> 95.914634 | E48: =E14*(E15-E16)/E15 -> 95.914634 | F48: =F14*(F15-F16)/F15 -> 95.914634 | G48: =G14*(G15-G16)/G15 -> 95.914634 | H48: =H14*(H15-H16)/H15 -> 95.914634 | I48: =I14*(I15-I16)/I15 -> 95.914634 | ... AA48: =AA14*(AA15-AA16)/AA15 -> 95.914634
A49: Parent dividend 2027 | B49: =B10*(1+B11) -> 1186.92 | C49: =C10*(1+C11) -> 1186.92 | D49: =D10*(1+D11) -> 1186.92 | E49: =E10*(1+E11) -> 1186.92 | F49: =F10*(1+F11) -> 1186.92 | G49: =G10*(1+G11) -> 1186.92 | H49: =H10*(1+H11) -> 1186.92 | I49: =I10*(1+I11) -> 1186.92 | ... AA49: =AA10*(1+AA11) -> 1186.92
A50: Total dividends, coupons, buyback 2027 | B50: =B49+B12+B48+B18 -> 1623.8346 | C50: =C49+C12+C48+C18 -> 1623.8346 | D50: =D49+D12+D48+D18 -> 1623.8346 | E50: =E49+E12+E48+E18 -> 1623.8346 | F50: =F49+F12+F48+F18 -> 1623.8346 | G50: =G49+G12+G48+G18 -> 1623.8346 | H50: =H49+H12+H48+H18 -> 1623.8346 | I50: =I49+I12+I48+I18 -> 1623.8346 | ... AA50: =AA49+AA12+AA48+AA18 -> 1623.8346
A51: Disposals cashed Jul-26 to Dec-27 | B51: =B19*B20 -> 1500 | C51: =C19*C20 -> 1500 | D51: =D19*D20 -> 1000 | E51: =E19*E20 -> 2000 | F51: =F19*F20 -> 1500 | G51: =G19*G20 -> 1500 | H51: =H19*H20 -> 1500 | I51: =I19*I20 -> 1500 | ... AA51: =AA19*AA20 -> 1500
A52: of which H2 2026 | B52: =B51*B21 -> 300 | C52: =C51*C21 -> 300 | D52: =D51*D21 -> 200 | E52: =E51*E21 -> 400 | F52: =F51*F21 -> 300 | G52: =G51*G21 -> 300 | H52: =H51*H21 -> 300 | I52: =I51*I21 -> 300 | ... AA52: =AA51*AA21 -> 300
A53: of which 2027 | B53: =B51-B52 -> 1200 | C53: =C51-C52 -> 1200 | D53: =D51-D52 -> 800 | E53: =E51-E52 -> 1600 | F53: =F51-F52 -> 1200 | G53: =G51-G52 -> 1200 | H53: =H51-H52 -> 1200 | I53: =I51-I52 -> 1200 | ... AA53: =AA51-AA52 -> 1200
A54: NFD 31/12/2026e | B54: =B5-B45+B47+B18-B52+B38 -> 22982.1 | C54: =C5-C45+C47+C18-C52+C38 -> 22982.1 | D54: =D5-D45+D47+D18-D52+D38 -> 23100 | E54: =E5-E45+E47+E18-E52+E38 -> 22882.1 | F54: =F5-F45+F47+F18-F52+F38 -> 22982.1 | G54: =G5-G45+G47+G18-G52+G38 -> 22982.1 | H54: =H5-H45+H47+H18-H52+H38 -> 22982.1 | I54: =I5-I45+I47+I18-I52+I38 -> 22982.1 | ... AA54: =AA5-AA45+AA47+AA18-AA52+AA38 -> 22982.1
A55: EBITDA 2026e | B55: =B26*(1+B23+B24)+B42*B32/12 -> 7468.6596 | C55: =C26*(1+C23+C24)+C42*C32/12 -> 7468.6596 | D55: =D26*(1+D23+D24)+D42*D32/12 -> 7468.6596 | E55: =E26*(1+E23+E24)+E42*E32/12 -> 7468.6596 | F55: =F26*(1+F23+F24)+F42*F32/12 -> 7468.6596 | G55: =G26*(1+G23+G24)+G42*G32/12 -> 7468.6596 | H55: =H26*(1+H23+H24)+H42*H32/12 -> 7468.6596 | I55: =I26*(1+I23+I24)+I42*I32/12 -> 7468.6596 | ... AA55: =AA26*(1+AA23+AA24)+AA42*AA32/12 -> 7468.6596
A56: Leverage 31/12/2026e | B56: =B54/B55 -> 3.0771385 | C56: =C54/C55 -> 3.0771385 | D56: =D54/D55 -> 3.0929245 | E56: =E54/E55 -> 3.0637492 | F56: =F54/F55 -> 3.0771385 | G56: =G54/G55 -> 3.0771385 | H56: =H54/H55 -> 3.0771385 | I56: =I54/I55 -> 3.0771385 | ... AA56: =AA54/AA55 -> 3.0771385
A57: Check vs guidance '3x or slightly above' | B57: =IF(ABS(B56-B35)<=0.15,"consistent","REVIEW") -> consistent | C57: =IF(ABS(C56-C35)<=0.15,"consistent","REVIEW") -> consistent | D57: =IF(ABS(D56-D35)<=0.15,"consistent","REVIEW") -> consistent | E57: =IF(ABS(E56-E35)<=0.15,"consistent","REVIEW") -> consistent | F57: =IF(ABS(F56-F35)<=0.15,"consistent","REVIEW") -> consistent | G57: =IF(ABS(G56-G35)<=0.15,"consistent","REVIEW") -> consistent | H57: =IF(ABS(H56-H35)<=0.15,"consistent","REVIEW") -> consistent | I57: =IF(ABS(I56-I35)<=0.15,"consistent","REVIEW") -> consistent | ... AA57: =IF(ABS(AA56-AA35)<=0.15,"consistent","REVIEW") -> consistent
A58: NFD 31/12/2027e before any new acquisition | B58: =B54-B46+B50-B53+B39 -> 22191.863 | C58: =C54-C46+C50-C53+C39 -> 22191.863 | D58: =D54-D46+D50-D53+D39 -> 23045.835 | E58: =E54-E46+E50-E53+E39 -> 21691.863 | F58: =F54-F46+F50-F53+F39 -> 22191.863 | G58: =G54-G46+G50-G53+G39 -> 22191.863 | H58: =H54-H46+H50-H53+H39 -> 22191.863 | I58: =I54-I46+I50-I53+I39 -> 22191.863 | ... AA58: =AA54-AA46+AA50-AA53+AA39 -> 22191.863
A59: EBITDA 2027e before disposals (trajectory or override) | B59: =IF(B33>0,B33,B26*(1+B23+B24)*(1+B25)+B42*(1+B25)+B43) -> 7938.3759 | C59: =IF(C33>0,C33,C26*(1+C23+C24)*(1+C25)+C42*(1+C25)+C43) -> 8000 | D59: =IF(D33>0,D33,D26*(1+D23+D24)*(1+D25)+D42*(1+D25)+D43) -> 7863.0153 | E59: =IF(E33>0,E33,E26*(1+E23+E24)*(1+E25)+E42*(1+E25)+E43) -> 8013.7365 | F59: =IF(F33>0,F33,F26*(1+F23+F24)*(1+F25)+F42*(1+F25)+F43) -> 7750 | G59: =IF(G33>0,G33,G26*(1+G23+G24)*(1+G25)+G42*(1+G25)+G43) -> 8250 | H59: =IF(H33>0,H33,H26*(1+H23+H24)*(1+H25)+H42*(1+H25)+H43) -> 7863.0153 | I59: =IF(I33>0,I33,I26*(1+I23+I24)*(1+I25)+I42*(1+I25)+I43) -> 8013.7365 | ... AA59: =IF(AA33>0,AA33,AA26*(1+AA23+AA24)*(1+AA25)+AA42*(1+AA25)+AA43) -> 7938.3759
A60: EBITDA removed by disposals (H2-26 full year, 2027 half year) | B60: =(B52+0.5*B53)/B22 -> 90 | C60: =(C52+0.5*C53)/C22 -> 90 | D60: =(D52+0.5*D53)/D22 -> 75 | E60: =(E52+0.5*E53)/E22 -> 100 | F60: =(F52+0.5*F53)/F22 -> 90 | G60: =(G52+0.5*G53)/G22 -> 90 | H60: =(H52+0.5*H53)/H22 -> 90 | I60: =(I52+0.5*I53)/I22 -> 90 | ... AA60: =(AA52+0.5*AA53)/AA22 -> 90
A61: EBITDA 2027e | B61: =B59-B60 -> 7848.3759 | C61: =C59-C60 -> 7910 | D61: =D59-D60 -> 7788.0153 | E61: =E59-E60 -> 7913.7365 | F61: =F59-F60 -> 7660 | G61: =G59-G60 -> 8160 | H61: =H59-H60 -> 7773.0153 | I61: =I59-I60 -> 7923.7365 | ... AA61: =AA59-AA60 -> 7848.3759
A62: Leverage 31/12/2027e before new acquisitions | B62: =B58/B61 -> 2.8275739 | C62: =C58/C61 -> 2.8055453 | D62: =D58/D61 -> 2.9591409 | E62: =E58/E61 -> 2.7410393 | F62: =F58/F61 -> 2.8971101 | G62: =G58/G61 -> 2.7195911 | H62: =H58/H61 -> 2.8549877 | I62: =I58/I61 -> 2.8006816 | ... AA62: =AA58/AA61 -> 2.8275739
A63: Maximum NFD at cap | B63: =B34*B61 -> 23545.128 | C63: =C34*C61 -> 23730 | D63: =D34*D61 -> 23364.046 | E63: =E34*E61 -> 23741.209 | F63: =F34*F61 -> 22980 | G63: =G34*G61 -> 24480 | H63: =H34*H61 -> 23319.046 | I63: =I34*I61 -> 23771.209 | ... AA63: =AA34*AA61 -> 24329.965
A64: Leverage headroom 31/12/2027 (debt room) | B64: =B63-B58 -> 1353.2647 | C64: =C63-C58 -> 1538.137 | D64: =D63-D58 -> 318.21127 | E64: =E63-E58 -> 2049.3464 | F64: =F63-F58 -> 788.13698 | G64: =G63-G58 -> 2288.137 | H64: =H63-H58 -> 1127.1829 | I64: =I63-I58 -> 1579.3464 | ... AA64: =AA63-AA58 -> 2138.1023
A65: ACQUISITION CAPACITY Jul-26 to Dec-27 (EV, EUR m) | B65: =B64/(1-B34*B37/B36) -> 1353.2647 | C65: =C64/(1-C34*C37/C36) -> 1538.137 | D65: =D64/(1-D34*D37/D36) -> 318.21127 | E65: =E64/(1-E34*E37/E36) -> 2927.6378 | F65: =F64/(1-F34*F37/F36) -> 788.13698 | G65: =G64/(1-G34*G37/G36) -> 2288.137 | H65: =H64/(1-H34*H37/H36) -> 1127.1829 | I65: =I64/(1-I34*I37/I36) -> 1579.3464 | ... AA65: =AA64/(1-AA34*AA37/AA36) -> 2138.1023
A66: Source 1 - retained FCF (FCF less dividends, coupons, buyback, FX) | B66: =B45+B46-B47-B18-B50-B38-B39 -> 856.13698 | C66: =C45+C46-C47-C18-C50-C38-C39 -> 856.13698 | D66: =D45+D46-D47-D18-D50-D38-D39 -> 502.16537 | E66: =E45+E46-E47-E18-E50-E38-E39 -> 856.13698 | F66: =F45+F46-F47-F18-F50-F38-F39 -> 856.13698 | G66: =G45+G46-G47-G18-G50-G38-G39 -> 856.13698 | H66: =H45+H46-H47-H18-H50-H38-H39 -> 856.13698 | I66: =I45+I46-I47-I18-I50-I38-I39 -> 856.13698 | ... AA66: =AA45+AA46-AA47-AA18-AA50-AA38-AA39 -> 856.13698
A67: Source 2 - disposals, net of the debt room they cost | B67: =B51-B34*B60 -> 1230 | C67: =C51-C34*C60 -> 1230 | D67: =D51-D34*D60 -> 775 | E67: =E51-E34*E60 -> 1700 | F67: =F51-F34*F60 -> 1230 | G67: =G51-G34*G60 -> 1230 | H67: =H51-H34*H60 -> 1230 | I67: =I51-I34*I60 -> 1230 | ... AA67: =AA51-AA34*AA60 -> 1221
A68: Source 3 - leverage room vs Jun-26 debt (cap x EBITDA before disposals - NFD Jun-26) | B68: =B34*B59-B5 -> -732.87232 | C68: =C34*C59-C5 -> -548 | D68: =D34*D59-D5 -> -958.9541 | E68: =E34*E59-E5 -> -506.79053 | F68: =F34*F59-F5 -> -1298 | G68: =G34*G59-G5 -> 202 | H68: =H34*H59-H5 -> -958.9541 | I68: =I34*I59-I5 -> -506.79053 | ... AA68: =AA34*AA59-AA5 -> 60.965274
A69: Source 4 - acquired EBITDA counted in ratio (pro forma uplift) | B69: =B65-B64 -> 0 | C69: =C65-C64 -> 0 | D69: =D65-D64 -> 0 | E69: =E65-E64 -> 878.29133 | F69: =F65-F64 -> 0 | G69: =G65-G64 -> 0 | H69: =H65-H64 -> 0 | I69: =I65-I64 -> 0 | ... AA69: =AA65-AA64 -> 0
A70: Check: sources sum to capacity | B70: =ROUND(B66+B67+B68+B69-B65,6) -> 0 | C70: =ROUND(C66+C67+C68+C69-C65,6) -> 0 | D70: =ROUND(D66+D67+D68+D69-D65,6) -> 0 | E70: =ROUND(E66+E67+E68+E69-E65,6) -> 0 | F70: =ROUND(F66+F67+F68+F69-F65,6) -> 0 | G70: =ROUND(G66+G67+G68+G69-G65,6) -> 0 | H70: =ROUND(H66+H67+H68+H69-H65,6) -> 0 | I70: =ROUND(I66+I67+I68+I69-I65,6) -> 0 | ... AA70: =ROUND(AA66+AA67+AA68+AA69-AA65,6) -> 0

Sheet Tornado
A1: Block 5 - one-way sensitivity of acquisition capacity (EUR m)
A2: Base capacity | B2: =Engine!$B$65 -> 1353.2647
A4: Driver | B4: Low input | C4: High input | D4: Capacity @ low | E4: Capacity @ high | F4: Swing | G4: Rank key
A5: EBITDA 2027 level | B5: =Engine!F33 -> 7750 | C5: =Engine!G33 -> 8250 | D5: =Engine!$F$65 -> 788.13698 | E5: =Engine!$G$65 -> 2288.137 | F5: =ABS(E5-D5) -> 1500 | G5: =F5+ROW()/1000000 -> 1500
A6: Organic EBITDA growth 2027 | B6: =Engine!H25 -> 0.04 | C6: =Engine!I25 -> 0.06 | D6: =Engine!$H$65 -> 1127.1829 | E6: =Engine!$I$65 -> 1579.3464 | F6: =ABS(E6-D6) -> 452.16356 | G6: =F6+ROW()/1000000 -> 452.16357
A7: Net FCF growth p.a. | B7: =Engine!J7 -> -0.03 | C7: =Engine!K7 -> 0.05 | D7: =Engine!$J$65 -> 1194.3332 | E7: =Engine!$K$65 -> 1478.938 | F7: =ABS(E7-D7) -> 284.6048 | G7: =F7+ROW()/1000000 -> 284.60481
A8: Disposals cashed by end-2027 | B8: =Engine!L20 -> 0.5 | C8: =Engine!M20 -> 1 | D8: =Engine!$L$65 -> 943.26467 | E8: =Engine!$M$65 -> 1763.2647 | F8: =ABS(E8-D8) -> 820 | G8: =F8+ROW()/1000000 -> 820.00001
A9: Multiple on assets sold | B9: =Engine!N22 -> 7 | C9: =Engine!O22 -> 13 | D9: =Engine!$N$65 -> 1237.5504 | E9: =Engine!$O$65 -> 1415.5724 | F9: =ABS(E9-D9) -> 178.02198 | G9: =F9+ROW()/1000000 -> 178.02199
A10: Parent dividend growth 2027 | B10: =Engine!P11 -> 0.04 | C10: =Engine!Q11 -> 0.1 | D10: =Engine!$P$65 -> 1397.2247 | E10: =Engine!$Q$65 -> 1331.2847 | F10: =ABS(E10-D10) -> 65.94 | G10: =F10+ROW()/1000000 -> 65.94001
A11: FX / other on NFD 2027 (EUR m) | B11: =Engine!R39 -> 400 | C11: =Engine!S39 -> -400 | D11: =Engine!$R$65 -> 953.26467 | E11: =Engine!$S$65 -> 1753.2647 | F11: =ABS(E11-D11) -> 800 | G11: =F11+ROW()/1000000 -> 800.00001
A12: Acquired EBITDA in 2027 ratio | B12: =Engine!T37 -> 0 | C12: =Engine!U37 -> 1 | D12: =Engine!$T$65 -> 1353.2647 | E12: =Engine!$U$65 -> 1933.2352 | F12: =ABS(E12-D12) -> 579.97057 | G12: =F12+ROW()/1000000 -> 579.97058
A13: Multiple paid on acquisitions | B13: =Engine!V36 -> 8 | C13: =Engine!W36 -> 12 | D13: =Engine!$V$65 -> 1353.2647 | E13: =Engine!$W$65 -> 1353.2647 | F13: =ABS(E13-D13) -> 0 | G13: =F13+ROW()/1000000 -> 1.3e-05
A14: Clean Earth EV/EBITDA (sets its EBITDA) | B14: =Engine!X28 -> 11.5 | C14: =Engine!Y28 -> 8.5 | D14: =Engine!$X$65 -> 1230.4193 | E14: =Engine!$Y$65 -> 1480.3607 | F14: =ABS(E14-D14) -> 249.94143 | G14: =F14+ROW()/1000000 -> 249.94145
A15: Leverage cap | B15: =Engine!Z34 -> 2.9 | C15: =Engine!AA34 -> 3.1 | D15: =Engine!$Z$65 -> 568.42708 | E15: =Engine!$AA$65 -> 2138.1023 | F15: =ABS(E15-D15) -> 1569.6752 | G15: =F15+ROW()/1000000 -> 1569.6752
A17: Ranked by swing
A18: Rank / driver | B18: Capacity @ low | C18: Capacity @ high | D18: Swing
A19: ="1. "&INDEX($A$5:$A$15,MATCH(LARGE($G$5:$G$15,1),$G$5:$G$15,0)) -> 1. Leverage cap | B19: =INDEX($D$5:$D$15,MATCH(LARGE($G$5:$G$15,1),$G$5:$G$15,0)) -> 568.42708 | C19: =INDEX($E$5:$E$15,MATCH(LARGE($G$5:$G$15,1),$G$5:$G$15,0)) -> 2138.1023 | D19: =INDEX($F$5:$F$15,MATCH(LARGE($G$5:$G$15,1),$G$5:$G$15,0)) -> 1569.6752
A20: ="2. "&INDEX($A$5:$A$15,MATCH(LARGE($G$5:$G$15,2),$G$5:$G$15,0)) -> 2. EBITDA 2027 level | B20: =INDEX($D$5:$D$15,MATCH(LARGE($G$5:$G$15,2),$G$5:$G$15,0)) -> 788.13698 | C20: =INDEX($E$5:$E$15,MATCH(LARGE($G$5:$G$15,2),$G$5:$G$15,0)) -> 2288.137 | D20: =INDEX($F$5:$F$15,MATCH(LARGE($G$5:$G$15,2),$G$5:$G$15,0)) -> 1500
A21: ="3. "&INDEX($A$5:$A$15,MATCH(LARGE($G$5:$G$15,3),$G$5:$G$15,0)) -> 3. Disposals cashed by end-2027 | B21: =INDEX($D$5:$D$15,MATCH(LARGE($G$5:$G$15,3),$G$5:$G$15,0)) -> 943.26467 | C21: =INDEX($E$5:$E$15,MATCH(LARGE($G$5:$G$15,3),$G$5:$G$15,0)) -> 1763.2647 | D21: =INDEX($F$5:$F$15,MATCH(LARGE($G$5:$G$15,3),$G$5:$G$15,0)) -> 820
A22: ="4. "&INDEX($A$5:$A$15,MATCH(LARGE($G$5:$G$15,4),$G$5:$G$15,0)) -> 4. FX / other on NFD 2027 (EUR m) | B22: =INDEX($D$5:$D$15,MATCH(LARGE($G$5:$G$15,4),$G$5:$G$15,0)) -> 953.26467 | C22: =INDEX($E$5:$E$15,MATCH(LARGE($G$5:$G$15,4),$G$5:$G$15,0)) -> 1753.2647 | D22: =INDEX($F$5:$F$15,MATCH(LARGE($G$5:$G$15,4),$G$5:$G$15,0)) -> 800
A23: ="5. "&INDEX($A$5:$A$15,MATCH(LARGE($G$5:$G$15,5),$G$5:$G$15,0)) -> 5. Acquired EBITDA in 2027 ratio | B23: =INDEX($D$5:$D$15,MATCH(LARGE($G$5:$G$15,5),$G$5:$G$15,0)) -> 1353.2647 | C23: =INDEX($E$5:$E$15,MATCH(LARGE($G$5:$G$15,5),$G$5:$G$15,0)) -> 1933.2352 | D23: =INDEX($F$5:$F$15,MATCH(LARGE($G$5:$G$15,5),$G$5:$G$15,0)) -> 579.97057
A24: ="6. "&INDEX($A$5:$A$15,MATCH(LARGE($G$5:$G$15,6),$G$5:$G$15,0)) -> 6. Organic EBITDA growth 2027 | B24: =INDEX($D$5:$D$15,MATCH(LARGE($G$5:$G$15,6),$G$5:$G$15,0)) -> 1127.1829 | C24: =INDEX($E$5:$E$15,MATCH(LARGE($G$5:$G$15,6),$G$5:$G$15,0)) -> 1579.3464 | D24: =INDEX($F$5:$F$15,MATCH(LARGE($G$5:$G$15,6),$G$5:$G$15,0)) -> 452.16356
A25: ="7. "&INDEX($A$5:$A$15,MATCH(LARGE($G$5:$G$15,7),$G$5:$G$15,0)) -> 7. Net FCF growth p.a. | B25: =INDEX($D$5:$D$15,MATCH(LARGE($G$5:$G$15,7),$G$5:$G$15,0)) -> 1194.3332 | C25: =INDEX($E$5:$E$15,MATCH(LARGE($G$5:$G$15,7),$G$5:$G$15,0)) -> 1478.938 | D25: =INDEX($F$5:$F$15,MATCH(LARGE($G$5:$G$15,7),$G$5:$G$15,0)) -> 284.6048
A26: ="8. "&INDEX($A$5:$A$15,MATCH(LARGE($G$5:$G$15,8),$G$5:$G$15,0)) -> 8. Clean Earth EV/EBITDA (sets its EBITDA) | B26: =INDEX($D$5:$D$15,MATCH(LARGE($G$5:$G$15,8),$G$5:$G$15,0)) -> 1230.4193 | C26: =INDEX($E$5:$E$15,MATCH(LARGE($G$5:$G$15,8),$G$5:$G$15,0)) -> 1480.3607 | D26: =INDEX($F$5:$F$15,MATCH(LARGE($G$5:$G$15,8),$G$5:$G$15,0)) -> 249.94143
A27: ="9. "&INDEX($A$5:$A$15,MATCH(LARGE($G$5:$G$15,9),$G$5:$G$15,0)) -> 9. Multiple on assets sold | B27: =INDEX($D$5:$D$15,MATCH(LARGE($G$5:$G$15,9),$G$5:$G$15,0)) -> 1237.5504 | C27: =INDEX($E$5:$E$15,MATCH(LARGE($G$5:$G$15,9),$G$5:$G$15,0)) -> 1415.5724 | D27: =INDEX($F$5:$F$15,MATCH(LARGE($G$5:$G$15,9),$G$5:$G$15,0)) -> 178.02198
A28: ="10. "&INDEX($A$5:$A$15,MATCH(LARGE($G$5:$G$15,10),$G$5:$G$15,0)) -> 10. Parent dividend growth 2027 | B28: =INDEX($D$5:$D$15,MATCH(LARGE($G$5:$G$15,10),$G$5:$G$15,0)) -> 1397.2247 | C28: =INDEX($E$5:$E$15,MATCH(LARGE($G$5:$G$15,10),$G$5:$G$15,0)) -> 1331.2847 | D28: =INDEX($F$5:$F$15,MATCH(LARGE($G$5:$G$15,10),$G$5:$G$15,0)) -> 65.94
A29: ="11. "&INDEX($A$5:$A$15,MATCH(LARGE($G$5:$G$15,11),$G$5:$G$15,0)) -> 11. Multiple paid on acquisitions | B29: =INDEX($D$5:$D$15,MATCH(LARGE($G$5:$G$15,11),$G$5:$G$15,0)) -> 1353.2647 | C29: =INDEX($E$5:$E$15,MATCH(LARGE($G$5:$G$15,11),$G$5:$G$15,0)) -> 1353.2647 | D29: =INDEX($F$5:$F$15,MATCH(LARGE($G$5:$G$15,11),$G$5:$G$15,0)) -> 0

Sheet Rating
A1: Rating cross-check - is the agency trigger tighter than 3x? (LOW CONFIDENCE until PDF read)
A3: Moody's forecast FFO/net debt 2027 | B3: =Inputs!$C$67 -> 0.195 | C3: Moody's metric, Moody's-adjusted debt: not comparable with Veolia NFD.
A4: Downgrade threshold (judgement on 'high teens') | B4: =Inputs!$C$68 -> 0.18
A5: Extra debt tolerable before trigger, as % of Moody's forecast debt | B5: =B3/B4-1 -> 0.083333333 | C5: FFO held constant: the acquired company's FFO would add back some room.
A6: Applied to base-case NFD 31/12/2027 before M&A (proxy) | B6: =B5*Engine!$B$58 -> 1849.3219 | C6: Proxy only: assumes Moody's forecast already embeds Veolia's plan.
A7: Compare: leverage headroom at 3.0x, base case | B7: =Engine!$B$64 -> 1353.2647
A8: Which constraint binds? | B8: =IF(B6<B7,"Rating trigger","3x commitment") -> 3x commitment | C8: To be redone once the Moody's and S&P reports are attached.
